shorthandai.py
shorthandai-0.0.11.dist-info/LICENSE
shorthandai-0.0.11.dist-info/METADATA
shorthandai-0.0.11.dist-info/WHEEL
shorthandai-0.0.11.dist-info/top_level.txt
shorthandai-0.0.11.dist-info/RECORD
