Metadata-Version: 2.1
Name: shorthandai
Version: 0.0.11
Summary: Python utilities for interacting with ShorthandAI data
Home-page: UNKNOWN
Author: Habanero Research LLC
License: UNKNOWN
Platform: UNKNOWN
Classifier: Programming Language :: Python :: 3
Classifier: License :: OSI Approved :: MIT License
Classifier: Operating System :: OS Independent
Requires-Python: >=3.8
License-File: LICENSE
Requires-Dist: requests
Requires-Dist: pandas
Requires-Dist: numpy
